deeper_search/__init__.py
deeper_search/search.py
deeper_search-0.2.dist-info/METADATA
deeper_search-0.2.dist-info/WHEEL
deeper_search-0.2.dist-info/top_level.txt
deeper_search-0.2.dist-info/RECORD
