Metadata-Version: 2.1
Name: deeper_search
Version: 0.2
Author-email: abubakarilyas624@gmail.com
Classifier: Programming Language :: Python :: 3
Classifier: License :: OSI Approved :: MIT License
Classifier: Operating System :: OS Independent
Requires-Python: >=3.6
Requires-Dist: requests
Requires-Dist: pydantic
